README.md
setup.cfg
setup.py
dsmlbc6/__init__.py
dsmlbc6/hi.py
dsmlbc6/data_prep/__init__.py
dsmlbc6/eda/__init__.py
dsmlbs6.egg-info/PKG-INFO
dsmlbs6.egg-info/SOURCES.txt
dsmlbs6.egg-info/dependency_links.txt
dsmlbs6.egg-info/top_level.txt