Metadata-Version: 2.1
Name: dsmlbs6
Version: 0.0.1
Summary: Data Science Tools
Home-page: https://github.com/...
Author: Zeynep Tetik
License: MIT
Keywords: data science,machine learning,bootcamp
Platform: UNKNOWN
Classifier: Development Status :: 4 - Beta
Classifier: License :: OSI Approved :: MIT License
Classifier: Programming Language :: Python :: 2.7
Classifier: Programming Language :: Python :: 3.5
Classifier: Topic :: Scientific/Engineering
